{
    "format_version": "1.10.0",
    "minecraft:client_entity": {
        "description": {
            "animations": {
                "firing": "animation.rum139.firing",
                "normal": "animation.rum139.normal",
                "rum139": "controller.animation.rum139"
            },
            "geometry": {
                "default": "geometry.rum139"
            },
            "identifier": "us:rum139",
            "materials": {
                "default": "spider"
            },
            "render_controllers": [
                "controller.render.skeleton"
            ],
            "scripts": {
                "animate": [
                    "rum139"
                ]
            },
            // "spawn_egg": {
            //     "texture": "null",
            //     "texture_index": 0
            // },
            "textures": {
                "default": "textures/entity/rum139"
            }
        }
    }
}